{"__type__":"dragonBones.DragonBonesAsset","_name":"anim_lhdb_ske","_dragonBonesJson":"{\"frameRate\":24,\"armature\":[{\"canvas\":{\"width\":210,\"y\":-25,\"height\":439,\"color\":16777215,\"x\":-3},\"type\":\"Armature\",\"name\":\"Armature\",\"defaultActions\":[{\"gotoAndPlay\":\"newAnimation\"}],\"ik\":[],\"bone\":[{\"name\":\"root\",\"transform\":{\"y\":27}},{\"transform\":{\"y\":0.6,\"x\":-61.7},\"name\":\"baoshi3\",\"parent\":\"root\"},{\"transform\":{\"y\":23,\"x\":70.8},\"name\":\"dabaoshi_\",\"parent\":\"root\"},{\"length\":53,\"transform\":{\"y\":23,\"skX\":-93.8676,\"skY\":-93.8676,\"x\":12.1},\"parent\":\"root\",\"name\":\"ren\"},{\"transform\":{\"y\":-156.9,\"x\":22.2},\"name\":\"biyan\",\"parent\":\"root\"},{\"transform\":{\"y\":-118.7,\"x\":-56.4},\"name\":\"baoshi2\",\"parent\":\"root\"},{\"transform\":{\"y\":118.65,\"x\":-17.45},\"name\":\"baoshi44\",\"parent\":\"root\"},{\"transform\":{\"y\":4.8026,\"x\":177.7809},\"name\":\"zhengyan\",\"parent\":\"ren\"},{\"length\":58,\"transform\":{\"y\":55.1654,\"skX\":-159.8208,\"skY\":-159.8208,\"x\":107.3324},\"parent\":\"ren\",\"name\":\"zuoshoubi\"},{\"length\":57,\"transform\":{\"y\":-37.8973,\"skX\":-48.7571,\"skY\":-48.7571,\"x\":58.3982},\"parent\":\"ren\",\"name\":\"youshou\"},{\"transform\":{\"y\":-19.3828,\"x\":89.8621},\"name\":\"xiong\",\"parent\":\"ren\"},{\"length\":35,\"transform\":{\"y\":-5.0889,\"skX\":-145.1686,\"skY\":-145.1686,\"x\":130.8001},\"parent\":\"ren\",\"name\":\"qiantoufa\"},{\"length\":48,\"transform\":{\"y\":2.113,\"skX\":151.5282,\"skY\":151.5282,\"x\":68.0839},\"parent\":\"zuoshoubi\",\"name\":\"zuoshou\"}],\"aabb\":{\"width\":200.00000000000014,\"y\":-175.50000000000006,\"height\":329.00000000000006,\"x\":-103},\"slot\":[{\"name\":\"ren\",\"parent\":\"ren\",\"color\":{}},{\"z\":1,\"name\":\"qiantoufa\",\"parent\":\"qiantoufa\",\"color\":{}},{\"z\":2,\"name\":\"xiong\",\"parent\":\"xiong\",\"color\":{}},{\"z\":3,\"name\":\"zuoshoubi\",\"parent\":\"zuoshoubi\",\"color\":{}},{\"z\":4,\"name\":\"zuoshou\",\"parent\":\"zuoshou\",\"color\":{}},{\"z\":5,\"name\":\"youshou\",\"parent\":\"youshou\",\"color\":{}},{\"z\":6,\"displayIndex\":11,\"name\":\"baoshi2\",\"parent\":\"baoshi2\",\"color\":{}},{\"z\":7,\"name\":\"baoxiang\",\"parent\":\"root\",\"color\":{}},{\"z\":8,\"name\":\"xiaobaoshi\",\"parent\":\"root\",\"color\":{}},{\"z\":9,\"name\":\"dabaoshi2\",\"parent\":\"root\",\"color\":{}},{\"z\":10,\"name\":\"baoshi44\",\"parent\":\"baoshi44\",\"color\":{}},{\"z\":11,\"name\":\"baoshi222\",\"parent\":\"root\",\"color\":{}},{\"z\":12,\"name\":\"baoshi3\",\"parent\":\"baoshi3\",\"color\":{}},{\"z\":13,\"name\":\"dabaoshi_\",\"parent\":\"dabaoshi_\",\"color\":{}},{\"z\":14,\"name\":\"baoshidui\",\"parent\":\"root\",\"color\":{}},{\"z\":15,\"name\":\"biyan\",\"parent\":\"biyan\",\"color\":{}}],\"frameRate\":24,\"animation\":[{\"ffd\":[],\"playTimes\":0,\"duration\":48,\"ik\":[],\"frame\":[],\"bone\":[{\"frame\":[{\"transform\":{},\"duration\":39},{\"transform\":{},\"duration\":9}],\"name\":\"root\"},{\"frame\":[{\"tweenEasing\":0,\"transform\":{},\"duration\":24},{\"tweenEasing\":0,\"transform\":{\"scX\":1.1,\"y\":7.4,\"scY\":1.1},\"duration\":24},{\"transform\":{},\"duration\":0}],\"name\":\"baoshi3\"},{\"frame\":[{\"tweenEasing\":0,\"transform\":{},\"duration\":18},{\"tweenEasing\":0,\"transform\":{\"scX\":0.925,\"y\":-10.545,\"scY\":0.925,\"skX\":0.7272,\"skY\":0.7272},\"duration\":6},{\"tweenEasing\":0,\"transform\":{\"scX\":0.9,\"y\":-14.06,\"scY\":0.9},\"duration\":24},{\"transform\":{},\"duration\":0}],\"name\":\"dabaoshi_\"},{\"frame\":[{\"tweenEasing\":0,\"transform\":{},\"duration\":24},{\"tweenEasing\":0,\"transform\":{\"y\":2.84},\"duration\":24},{\"transform\":{},\"duration\":0}],\"name\":\"ren\"},{\"frame\":[{\"transform\":{},\"duration\":48}],\"name\":\"zhengyan\"},{\"frame\":[{\"transform\":{},\"duration\":2},{\"tweenEasing\":0,\"transform\":{},\"duration\":13},{\"tweenEasing\":0,\"transform\":{\"scX\":1.0295,\"scY\":1.0295},\"duration\":9},{\"tweenEasing\":0,\"transform\":{\"scX\":1.05,\"scY\":1.05},\"duration\":20},{\"tweenEasing\":0,\"transform\":{\"scX\":1.0083,\"scY\":1.0083},\"duration\":4},{\"transform\":{},\"duration\":0}],\"name\":\"xiong\"},{\"frame\":[{\"tweenEasing\":0,\"transform\":{},\"duration\":24},{\"tweenEasing\":0,\"transform\":{\"skX\":-4.6465,\"skY\":-4.6465},\"duration\":20},{\"tweenEasing\":0,\"transform\":{\"skX\":-1.1163,\"skY\":-1.1163},\"duration\":4},{\"transform\":{},\"duration\":0}],\"name\":\"youshou\"},{\"frame\":[{\"tweenEasing\":0,\"transform\":{},\"duration\":24},{\"tweenEasing\":0,\"transform\":{\"skX\":5.5188,\"skY\":5.5188},\"duration\":24},{\"transform\":{},\"duration\":0}],\"name\":\"zuoshoubi\"},{\"frame\":[{\"tweenEasing\":0,\"transform\":{},\"duration\":24},{\"tweenEasing\":0,\"transform\":{\"skX\":-4.8703,\"skY\":-4.8703},\"duration\":24},{\"transform\":{},\"duration\":0}],\"name\":\"zuoshou\"},{\"frame\":[{\"tweenEasing\":0,\"transform\":{},\"duration\":24},{\"tweenEasing\":0,\"transform\":{\"skX\":-2.0757,\"skY\":-2.0757},\"duration\":24},{\"transform\":{},\"duration\":0}],\"name\":\"qiantoufa\"},{\"frame\":[{\"transform\":{},\"duration\":48}],\"name\":\"baoshi44\"},{\"frame\":[{\"transform\":{},\"duration\":48}],\"name\":\"biyan\"},{\"frame\":[{\"transform\":{},\"duration\":48}],\"name\":\"baoshi2\"}],\"slot\":[{\"frame\":[{\"tweenEasing\":0,\"duration\":23},{\"tweenEasing\":0,\"color\":{\"aM\":0},\"duration\":25},{\"tweenEasing\":null,\"duration\":0}],\"name\":\"biyan\"},{\"frame\":[{\"displayIndex\":11,\"tweenEasing\":0,\"duration\":4},{\"displayIndex\":10,\"tweenEasing\":0,\"duration\":4},{\"displayIndex\":9,\"tweenEasing\":0,\"duration\":4},{\"displayIndex\":8,\"tweenEasing\":0,\"duration\":4},{\"displayIndex\":7,\"tweenEasing\":0,\"duration\":4},{\"displayIndex\":6,\"tweenEasing\":0,\"duration\":4},{\"displayIndex\":5,\"tweenEasing\":0,\"duration\":4},{\"displayIndex\":4,\"tweenEasing\":0,\"duration\":4},{\"displayIndex\":3,\"tweenEasing\":0,\"duration\":4},{\"displayIndex\":2,\"tweenEasing\":0,\"duration\":4},{\"displayIndex\":1,\"tweenEasing\":0,\"duration\":4},{\"tweenEasing\":0,\"duration\":4},{\"tweenEasing\":null,\"duration\":0}],\"name\":\"baoshi2\"}],\"name\":\"newAnimation\"}],\"skin\":[{\"slot\":[{\"display\":[{\"path\":\"ui_lhdb_donghua/baoshi44\",\"type\":\"image\",\"name\":\"ui_lhdb_donghua/baoshi44\",\"transform\":{\"y\":-25.15,\"x\":29.95}}],\"name\":\"baoshi44\"},{\"display\":[{\"path\":\"ui_lhdb_donghua/biyan\",\"type\":\"image\",\"name\":\"ui_lhdb_donghua/biyan\",\"transform\":{\"y\":0.9,\"x\":-7.2}}],\"name\":\"biyan\"},{\"display\":[{\"path\":\"ui_lhdb_donghua/baoshi3\",\"type\":\"image\",\"name\":\"ui_lhdb_donghua/baoshi3\",\"transform\":{\"y\":1.9,\"x\":3.2}}],\"name\":\"baoshi3\"},{\"display\":[{\"path\":\"ui_lhdb_donghua/xiong\",\"type\":\"image\",\"name\":\"ui_lhdb_donghua/xiong\",\"transform\":{\"y\":20.8232,\"skX\":93.8676,\"skY\":93.8676,\"x\":-7.7723}}],\"name\":\"xiong\"},{\"display\":[{\"path\":\"ui_lhdb_donghua/qiantoufa\",\"type\":\"image\",\"name\":\"ui_lhdb_donghua/qiantoufa\",\"transform\":{\"scX\":0.9842,\"y\":-23.0837,\"scY\":0.9842,\"skX\":-120.9638,\"skY\":-120.9638,\"x\":50.5235}}],\"name\":\"qiantoufa\"},{\"display\":[{\"path\":\"ui_lhdb_donghua/baoshi2\",\"type\":\"image\",\"name\":\"ui_lhdb_donghua/baoshi2\",\"transform\":{\"y\":-3.8,\"x\":7.9}},{\"path\":\"ui_lhdb_donghua/baoshi1\",\"type\":\"image\",\"name\":\"ui_lhdb_donghua/baoshi1\",\"transform\":{\"y\":-3.8,\"x\":5.9}},{\"path\":\"ui_lhdb_donghua/baoshi3_0\",\"type\":\"image\",\"name\":\"ui_lhdb_donghua/baoshi3_0\",\"transform\":{\"y\":-3.8,\"x\":10.4}},{\"path\":\"ui_lhdb_donghua/baoshi4\",\"type\":\"image\",\"name\":\"ui_lhdb_donghua/baoshi4\",\"transform\":{\"y\":-3.8,\"x\":8.9}},{\"path\":\"ui_lhdb_donghua/baoshi5\",\"type\":\"image\",\"name\":\"ui_lhdb_donghua/baoshi5\",\"transform\":{\"y\":-3.8,\"x\":9.4}},{\"path\":\"ui_lhdb_donghua/baoshi6\",\"type\":\"image\",\"name\":\"ui_lhdb_donghua/baoshi6\",\"transform\":{\"y\":-3.8,\"x\":10.9}},{\"path\":\"ui_lhdb_donghua/baoshi7\",\"type\":\"image\",\"name\":\"ui_lhdb_donghua/baoshi7\",\"transform\":{\"y\":-3.8,\"x\":11.9}},{\"path\":\"ui_lhdb_donghua/baoshi8\",\"type\":\"image\",\"name\":\"ui_lhdb_donghua/baoshi8\",\"transform\":{\"y\":-3.8,\"x\":13.4}},{\"path\":\"ui_lhdb_donghua/baoshi9\",\"type\":\"image\",\"name\":\"ui_lhdb_donghua/baoshi9\",\"transform\":{\"y\":-3.8,\"x\":8.9}},{\"path\":\"ui_lhdb_donghua/baoshi10\",\"type\":\"image\",\"name\":\"ui_lhdb_donghua/baoshi10\",\"transform\":{\"y\":-3.8,\"x\":8.9}},{\"path\":\"ui_lhdb_donghua/baoshi11\",\"type\":\"image\",\"name\":\"ui_lhdb_donghua/baoshi11\",\"transform\":{\"y\":-3.8,\"x\":8.4}},{\"path\":\"ui_lhdb_donghua/baosh_12\",\"type\":\"image\",\"name\":\"ui_lhdb_donghua/baosh_12\",\"transform\":{\"y\":-6.243,\"x\":5.7971}}],\"name\":\"baoshi2\"},{\"display\":[{\"path\":\"ui_lhdb_donghua/dabaoshi_\",\"type\":\"image\",\"name\":\"ui_lhdb_donghua/dabaoshi_\",\"transform\":{\"y\":5.5,\"x\":2.7}}],\"name\":\"dabaoshi_\"},{\"display\":[{\"path\":\"ui_lhdb_donghua/baoshi222\",\"type\":\"image\",\"name\":\"ui_lhdb_donghua/baoshi222\",\"transform\":{\"y\":96.5,\"x\":-17.5}}],\"name\":\"baoshi222\"},{\"display\":[{\"path\":\"ui_lhdb_donghua/zuoshou\",\"type\":\"image\",\"name\":\"ui_lhdb_donghua/zuoshou\",\"transform\":{\"y\":0.7234,\"skX\":102.1602,\"skY\":102.1602,\"x\":40.1485}}],\"name\":\"zuoshou\"},{\"display\":[{\"path\":\"ui_lhdb_donghua/dabaoshi2\",\"type\":\"image\",\"name\":\"ui_lhdb_donghua/dabaoshi2\",\"transform\":{\"y\":85,\"x\":72.5}}],\"name\":\"dabaoshi2\"},{\"display\":[{\"path\":\"ui_lhdb_donghua/zuoshoubi\",\"type\":\"image\",\"name\":\"ui_lhdb_donghua/zuoshoubi\",\"transform\":{\"y\":-2.4403,\"skX\":-106.3115,\"skY\":-106.3115,\"x\":29.3458}}],\"name\":\"zuoshoubi\"},{\"display\":[{\"path\":\"ui_lhdb_donghua/xiaobaoshi\",\"type\":\"image\",\"name\":\"ui_lhdb_donghua/xiaobaoshi\",\"transform\":{\"y\":110.5,\"x\":-84}}],\"name\":\"xiaobaoshi\"},{\"display\":[{\"path\":\"ui_lhdb_donghua/baoxiang\",\"type\":\"image\",\"name\":\"ui_lhdb_donghua/baoxiang\",\"transform\":{\"y\":85.5,\"x\":-61}}],\"name\":\"baoxiang\"},{\"display\":[{\"path\":\"ui_lhdb_donghua/baoshidui\",\"type\":\"image\",\"name\":\"ui_lhdb_donghua/baoshidui\",\"transform\":{\"y\":69.5,\"x\":-63.5}}],\"name\":\"baoshidui\"},{\"display\":[{\"path\":\"ui_lhdb_donghua/youshou\",\"type\":\"image\",\"name\":\"ui_lhdb_donghua/youshou\",\"transform\":{\"y\":4.0262,\"skX\":142.6247,\"skY\":142.6247,\"x\":41.2671}}],\"name\":\"youshou\"},{\"display\":[{\"path\":\"ui_lhdb_donghua/ren\",\"type\":\"image\",\"name\":\"ui_lhdb_donghua/ren\",\"transform\":{\"y\":-7.6544,\"skX\":93.8676,\"skY\":93.8676,\"x\":66.167}}],\"name\":\"ren\"}],\"name\":\"\"}]}],\"isGlobal\":0,\"name\":\"大厅图标动画\",\"version\":\"5.0\"}"}