{"__type__":"cc.SpriteAtlas","_name":"fish_5.plist","_spriteFrames":{"fish_00":{"__uuid__":"fdUxKvjyBC75WDOnuSfl6F"},"fish_01":{"__uuid__":"c2+QApcC1AS5ZLJyjCdvzl"},"fish_02":{"__uuid__":"d6EFW17l1De7KMg7JjDtyF"},"fish_03":{"__uuid__":"93piEWqplHd455jmgcaiiS"},"fish_04":{"__uuid__":"f2Bwg2N/lC2535JhvgH+K0"},"fish_05":{"__uuid__":"c5YS9qjMhK3b/3olahyzOv"},"fish_06":{"__uuid__":"72RHp/s8hID4cZDtxHJ2bD"},"fish_07":{"__uuid__":"85av+GkRxCfrD6CZDVrhj8"},"fish_08":{"__uuid__":"d7YLh8mdxFWqKPaT+bN7zZ"},"fish_09":{"__uuid__":"9cVVmw1QBAC6YmEEu/0gUC"},"fish_10":{"__uuid__":"62Al479bpA/YIM+yrOHGVo"},"fish_11":{"__uuid__":"5dVNGZN3tIKaaH1FBiiWxT"},"fish_12":{"__uuid__":"c2+kEDRXpLRaWJVwetwZe3"},"fish_13":{"__uuid__":"77PHnZw85NhL0G7OIgWJUi"},"fish_14":{"__uuid__":"e37kdOsBZH6atgCsm+kAVD"},"fish_15":{"__uuid__":"7co+ziyFlCMoZlGI+Zsb5E"},"fish_16":{"__uuid__":"c8kwlV5ipO7aezoW3If4sR"},"fish_17":{"__uuid__":"bfak+dlrlOkoNBT63Vg+NI"},"fish_18":{"__uuid__":"2fFHbjkjZEU6RheUaHIige"},"fish_19":{"__uuid__":"52ohIc4HBCyb4xja3PIZse"},"fish_20":{"__uuid__":"49dSyg+/JIAIJnkOoyaHz8"},"fish_21":{"__uuid__":"5dCa+jBH5EJYE566/7BSP5"},"fish_22":{"__uuid__":"46SBpknDtGBZ9HsSctUep6"},"fish_23":{"__uuid__":"73Dr8vtppGu5q24BUd7j7t"}}}