{"__type__":"dragonBones.DragonBonesAtlasAsset","_name":"lumian_tex","_atlasJson":"{\"width\":1024,\"SubTexture\":[{\"width\":640,\"y\":1,\"height\":360,\"name\":\"lu/背景\",\"x\":1},{\"width\":36,\"y\":587,\"height\":54,\"name\":\"lu/船\",\"x\":848},{\"width\":55,\"y\":587,\"height\":78,\"name\":\"lu/小船\",\"x\":791},{\"frameWidth\":159,\"y\":324,\"frameHeight\":197,\"width\":158,\"frameX\":-1,\"height\":196,\"name\":\"lu/楼\",\"frameY\":-1,\"x\":643},{\"width\":640,\"y\":363,\"height\":360,\"name\":\"lu/影子\",\"x\":1},{\"frameWidth\":608,\"y\":1365,\"frameHeight\":214,\"width\":608,\"frameX\":0,\"height\":214,\"name\":\"lu/路底\",\"frameY\":-1,\"x\":1},{\"frameWidth\":633,\"y\":1145,\"frameHeight\":219,\"width\":632,\"frameX\":0,\"height\":218,\"name\":\"lu/路面1\",\"frameY\":-1,\"x\":1},{\"frameWidth\":631,\"y\":924,\"frameHeight\":219,\"width\":631,\"frameX\":0,\"height\":219,\"name\":\"lu/路面2\",\"frameY\":-1,\"x\":1},{\"width\":89,\"y\":704,\"height\":144,\"name\":\"lu/水\",\"x\":786},{\"frameWidth\":181,\"y\":850,\"frameHeight\":65,\"width\":180,\"frameX\":-1,\"height\":64,\"name\":\"lu/路面光\",\"frameY\":0,\"x\":786},{\"width\":709,\"y\":725,\"height\":197,\"name\":\"lu/路延\",\"x\":1},{\"frameWidth\":464,\"y\":1581,\"frameHeight\":91,\"width\":464,\"frameX\":0,\"height\":90,\"name\":\"lu/路影\",\"frameY\":-1,\"x\":1},{\"width\":72,\"y\":522,\"height\":182,\"name\":\"lu/qi1\",\"x\":643},{\"width\":72,\"y\":522,\"height\":180,\"name\":\"lu/qi2\",\"x\":717},{\"width\":72,\"y\":706,\"height\":180,\"name\":\"lu/qi3\",\"x\":712},{\"frameWidth\":242,\"y\":924,\"frameHeight\":158,\"width\":241,\"frameX\":-1,\"height\":158,\"name\":\"lu/树\",\"frameY\":0,\"x\":634},{\"width\":69,\"y\":522,\"height\":63,\"name\":\"lu/飞艇\",\"x\":791},{\"frameWidth\":339,\"y\":1,\"frameHeight\":322,\"width\":337,\"frameX\":-1,\"height\":321,\"name\":\"lu/楼2\",\"frameY\":-1,\"x\":643}],\"height\":2048,\"name\":\"lumian\",\"imagePath\":\"lumian_tex.png\"}","_texture":{"__uuid__":"05DCXbfCZLLokTUi8qfLGq"},"texture":{"__uuid__":"05DCXbfCZLLokTUi8qfLGq"}}